CMakeLists.txt
LICENSE
MANIFEST.in
README.md
setup.py
bin/FitXrayData
bin/RunDigitizer
dactylos/CaenN6725.py
dactylos/__init__.py
dactylos.egg-info/PKG-INFO
dactylos.egg-info/SOURCES.txt
dactylos.egg-info/dependency_links.txt
dactylos.egg-info/not-zip-safe
dactylos.egg-info/requires.txt
dactylos.egg-info/top_level.txt
dactylos/analysis/__init__.py
dactylos/analysis/asic_projection.py
dactylos/analysis/file_inspector.py
dactylos/analysis/noisemodel.py
dactylos/analysis/overview_table.py
dactylos/analysis/spectrum_fits.py
dactylos/analysis/utils.py
dactylos/analysis/waveform_analysis.py
dactylos/analysis/shaping/__init__.py
dactylos/analysis/shaping/gauss_shaper.py
dactylos/analysis/shaping/shapers.py
dactylos/analysis/shaping/trapezoidal_shaper.h
dactylos/analysis/shaping/trapezoidal_shaper.py
include/CaenN6725.hh
include/trapezoidal_shaper.h
src/CaenN6725.cxx
src/module.cxx
src/trapezoidal_shaper.cxx